Workbook

Sheet RTM
A1: Requirement ID | B1: Requirement | C1: Stakeholder and source | D1: Scope reference | E1: Priority | F1: Acceptance IDs | G1: Design reference | H1: Issue / PR / code | I1: Test evidence | J1: Change reference | K1: Release evidence | L1: Implementation status | M1: ASR / quality driver | N1: Architecture / module | O1: Data / persistence impact | P1: Technology decision | Q1: ADR / risk reference | R1: Current requirement wording | S1: Expected / observed result | T1: Defect or remaining acceptance gap | U1: M3 execution evidence | V1: Evidence date / executor
A2: FR-001 | B2: Submit a service request | C2: Requester; PED §1.2, §2.1.1; MB §3 Requester | D2: SR-IN-01 | E2: =INDEX(Requirements!$C$2:$C$28,MATCH(A2,Requirements!$A$2:$A$28,0)) -> High | F2: AC-FR-001-1; AC-FR-001-2 | G2: ADR-M2-03; ADR-M2-04; ADR-M2-06; docs/decisions/README.md | H2: Planned. Design source PR #10 (architecture) / #11 (data/technology); no application implementation for this row. | I2: Creation and input validation not implemented | J2: M2 consolidation 2026-09-30; requirement/AC unchanged; M3 2026-10-13: evidence evolved; requirement/AC unchanged; CR-M3-C01. | K2: 15 Oct 2026; 668795a; PR17/CI pass. CONDITIONALLY READY: agreed M3 read/status increment, simulated staging only. PED Section 14. | L2: Planned | M2: Integrity; pilot performance | N2: Submission service (planned) | O2: ServiceRequest, Category, RequestHistory; atomic creation and idempotency | P2: ADR-M2-04: ASP.NET Core MVC/Razor; EF Core/Npgsql 8.0.11; PostgreSQL adapters/migrations implemented by Michael (PR14). | Q2: R-015; R-036 | R2: =INDEX(Requirements!$B$2:$B$28,MATCH(A2,Requirements!$A$2:$A$28,0)) -> Allow requesters to submit a request with a category, description and location. | S2: Not executed for complete acceptance. | T2: Request creation and input-validation endpoint absent. | U2: No complete M3 execution evidence; see docs/release-evidence.md. | V2: 2026-10-13 evidence review.
A3: FR-002 | B3: Controlled request categories | C3: Requester; Staff; PED §2.1.1, A-02; MB §3 Requester | D3: SR-IN-02 | E3: =INDEX(Requirements!$C$2:$C$28,MATCH(A3,Requirements!$A$2:$A$28,0)) -> High | F3: AC-FR-002-1; AC-FR-002-2 | G3: ADR-M2-03; ADR-M2-04; docs/decisions/README.md | H3: Planned. Design source PR #10 (architecture) / #11 (data/technology); no application implementation for this row. | I3: Controlled catalogue and persistent keys not implemented | J3: M2 consolidation 2026-09-30; requirement/AC unchanged; M3 2026-10-13: evidence evolved; requirement/AC unchanged; CR-M3-C01. | K3: 15 Oct 2026; 668795a; PR17/CI pass. CONDITIONALLY READY: agreed M3 read/status increment, simulated staging only. PED Section 14. | L3: Planned | M3: Integrity | N3: Category catalogue (planned) | O3: Category FK; retain referenced category | P3: ADR-M2-04: ASP.NET Core MVC/Razor; EF Core/Npgsql 8.0.11; PostgreSQL adapters/migrations implemented by Michael (PR14). | Q3: R-019 | R3: =INDEX(Requirements!$B$2:$B$28,MATCH(A3,Requirements!$A$2:$A$28,0)) -> Use a predefined list of request categories. | S3: Not executed for complete acceptance. | T3: Controlled category catalogue/enforced category key absent. | U3: No complete M3 execution evidence; see docs/release-evidence.md. | V3: 2026-10-13 evidence review.
A4: FR-003 | B4: View own request status | C4: Requester; PED §1.2, §2.1.1; MB §3 Requester | D4: SR-IN-03 | E4: =INDEX(Requirements!$C$2:$C$28,MATCH(A4,Requirements!$A$2:$A$28,0)) -> High | F4: AC-FR-003-1; AC-FR-003-2 | G4: ADR-M2-01; ADR-M2-03; ADR-M2-04; ADR-M2-05; ADR-M2-06; docs/decisions/README.md | H4: src/CivicConnect.Web/: RequestQueryService; RequestAccessPolicy; EfRequestReader; RequestStatusService. M2 PR12; M3 PR14; published combined implementation 668795a (PR17). | I4: E01/E02/A04; S01/S03/H04/H05/H07; passed 2026-10-13 where mapped; docs/testing-m3.md. | J4: M2 requirement/AC unchanged; CR-M3-C01 retained. Bianca/Michael review and PR17 approvals: 14 Oct. Published 668795a; CI verified; docs 15 Oct 2026. | K4: 15 Oct 2026; 668795a; PR17/CI pass. CONDITIONALLY READY: agreed M3 read/status increment, simulated staging only. PED Section 14. | L4: In Development | M4: Access isolation | N4: RequestsController; RequestQueryService | O4: Michael EF Core/PostgreSQL reader and persisted synthetic requests/notes; authorised application projection. | P4: ADR-M2-04: ASP.NET Core MVC/Razor; EF Core/Npgsql 8.0.11; PostgreSQL adapters/migrations implemented by Michael (PR14). | Q4: R-013; R-017 | R4: =INDEX(Requirements!$B$2:$B$28,MATCH(A4,Requirements!$A$2:$A$28,0)) -> Allow requesters to view the current status of their own requests. | S4: Owner reads saved Closed status/time and permitted notes; foreign record returns 404. | T4: Full live account/UI acceptance pending. See docs/defects.md and technical-debt.md. | U4: docs/testing-m3.md; docs/evidence/m3/personal-20261013-181846/ (integration.txt, regression.txt, database.txt; mapped IDs in column I). | V4: 2026-10-13 18:18-18:19 SAST; Cameron Purdon 601963; f774bf8.
A5: FR-004 | B5: View own request history | C5: Requester; PED §1.2, §2.1.1; MB §3 Requester | D5: SR-IN-04 | E5: =INDEX(Requirements!$C$2:$C$28,MATCH(A5,Requirements!$A$2:$A$28,0)) -> Medium | F5: AC-FR-004-1; AC-FR-004-2 | G5: ADR-M2-03; ADR-M2-04; ADR-M2-05; ADR-M2-06; docs/decisions/README.md | H5: Planned. Design source PR #10 (architecture) / #11 (data/technology); no application implementation for this row. | I5: List/history query not implemented | J5: M2 consolidation 2026-09-30; requirement/AC unchanged; M3 2026-10-13: evidence evolved; requirement/AC unchanged; CR-M3-C01. | K5: 15 Oct 2026; 668795a; PR17/CI pass. CONDITIONALLY READY: agreed M3 read/status increment, simulated staging only. PED Section 14. | L5: Planned | M5: Access isolation | N5: Requester history query (planned) | O5: Requester-scoped ServiceRequest collection | P5: ADR-M2-04: ASP.NET Core MVC/Razor; EF Core/Npgsql 8.0.11; PostgreSQL adapters/migrations implemented by Michael (PR14). | Q5: R-013 | R5: =INDEX(Requirements!$B$2:$B$28,MATCH(A5,Requirements!$A$2:$A$28,0)) -> Allow requesters to view their previous requests. | S5: Not executed for complete acceptance. | T5: Own request history/list workflow absent. | U5: No complete M3 execution evidence; see docs/release-evidence.md. | V5: 2026-10-13 evidence review.
A6: FR-005 | B6: Requester feedback | C6: Requester; PED §2.1.1; §5.2 concern 5; MB §3 Requester | D6: SR-IN-05 | E6: =INDEX(Requirements!$C$2:$C$28,MATCH(A6,Requirements!$A$2:$A$28,0)) -> Medium | F6: AC-FR-005-1; AC-FR-005-2 | G6: ADR-M2-02; ADR-M2-03; ADR-M2-04; ADR-M2-06; docs/decisions/README.md | H6: src/CivicConnect.Web/: RequestStatusService; EfRequestStatusWriter; EfRequestReader. M2 PR12; M3 PR14; published combined implementation 668795a (PR17). | I6: E01/E02; passed 2026-10-13 where mapped; docs/testing-m3.md. | J6: M2 requirement/AC unchanged; CR-M3-C01 retained. Bianca/Michael review and PR17 approvals: 14 Oct. Published 668795a; CI verified; docs 15 Oct 2026. | K6: 15 Oct 2026; 668795a; PR17/CI pass. CONDITIONALLY READY: agreed M3 read/status increment, simulated staging only. PED Section 14. | L6: In Development | M6: Integrity; access isolation | N6: RequestStatusService; transactional public feedback; authorised feedback projection | O6: PostgreSQL status/history/public-note transaction and optimistic version; broader schema/acceptance gaps remain. | P6: ADR-M2-04: ASP.NET Core MVC/Razor; EF Core/Npgsql 8.0.11; PostgreSQL adapters/migrations implemented by Michael (PR14). | Q6: R-027; R-028 | R6: =INDEX(Requirements!$B$2:$B$28,MATCH(A6,Requirements!$A$2:$A$28,0)) -> Provide requester feedback when a request is accepted, rejected, updated or completed. | S6: Status changes create persistent public feedback; rejection has a reason. | T6: Event/date presentation and full feedback scope pending. See docs/defects.md and technical-debt.md. | U6: docs/testing-m3.md; docs/evidence/m3/personal-20261013-181846/ (integration.txt, regression.txt, database.txt; mapped IDs in column I). | V6: 2026-10-13 18:18-18:19 SAST; Cameron Purdon 601963; f774bf8.
A7: FR-006 | B7: Authorised staff request list | C7: Staff; PED §1.2, §2.1.1, §2.2.3; MB §3 Staff | D7: SR-IN-06 | E7: =INDEX(Requirements!$C$2:$C$28,MATCH(A7,Requirements!$A$2:$A$28,0)) -> High | F7: AC-FR-006-1; AC-FR-006-2 | G7: ADR-M2-03; ADR-M2-04; ADR-M2-05; ADR-M2-06; docs/decisions/README.md | H7: src/CivicConnect.Web/: RequestAccessPolicy; request detail boundary only. M2 PR12; M3 PR14; published combined implementation 668795a (PR17). | I7: S05/H09/BB05; passed 2026-10-13 where mapped; docs/testing-m3.md. | J7: M2 requirement/AC unchanged; CR-M3-C01 retained. Bianca/Michael review and PR17 approvals: 14 Oct. Published 668795a; CI verified; docs 15 Oct 2026. | K7: 15 Oct 2026; 668795a; PR17/CI pass. CONDITIONALLY READY: agreed M3 read/status increment, simulated staging only. PED Section 14. | L7: In Development | M7: Access isolation | N7: Staff list query (planned) | O7: Category permission filter before counts/pagination | P7: ADR-M2-04: ASP.NET Core MVC/Razor; EF Core/Npgsql 8.0.11; PostgreSQL adapters/migrations implemented by Michael (PR14). | Q7: R-013; R-032 | R7: =INDEX(Requirements!$B$2:$B$28,MATCH(A7,Requirements!$A$2:$A$28,0)) -> Allow staff to view requests permitted by their role and assigned categories. | S7: Outside-category detail/mutation denied. | T7: Authorised staff list absent. See docs/defects.md and technical-debt.md. | U7: docs/testing-m3.md; docs/evidence/m3/personal-20261013-181846/ (integration.txt, regression.txt, database.txt; mapped IDs in column I). | V7: 2026-10-13 18:18-18:19 SAST; Cameron Purdon 601963; f774bf8.
A8: FR-007 | B8: Search, filter and sort | C8: Staff; PED §2.1.1; MB §3 Staff | D8: SR-IN-07 | E8: =INDEX(Requirements!$C$2:$C$28,MATCH(A8,Requirements!$A$2:$A$28,0)) -> Medium | F8: AC-FR-007-1; AC-FR-007-2 | G8: ADR-M2-03; ADR-M2-04; ADR-M2-05; ADR-M2-06; docs/decisions/README.md | H8: Planned. Design source PR #10 (architecture) / #11 (data/technology); no application implementation for this row. | I8: No search, sorting or load evidence | J8: M2 consolidation 2026-09-30; requirement/AC unchanged; M3 2026-10-13: evidence evolved; requirement/AC unchanged; CR-M3-C01. | K8: 15 Oct 2026; 668795a; PR17/CI pass. CONDITIONALLY READY: agreed M3 read/status increment, simulated staging only. PED Section 14. | L8: Planned | M8: Pilot performance; access isolation | N8: Search/filter query (planned) | O8: Permission-constrained sort/filter/index strategy | P8: ADR-M2-04: ASP.NET Core MVC/Razor; EF Core/Npgsql 8.0.11; PostgreSQL adapters/migrations implemented by Michael (PR14). | Q8: R-016; R-022 | R8: =INDEX(Requirements!$B$2:$B$28,MATCH(A8,Requirements!$A$2:$A$28,0)) -> Allow staff to search requests and filter by status, category, date and priority, and sort by date or priority. | S8: Not executed for complete acceptance. | T8: Search/filter/sort workflow absent. | U8: No complete M3 execution evidence; see docs/release-evidence.md. | V8: 2026-10-13 evidence review.
A9: FR-008 | B9: Full request details | C9: Staff; PED §2.1.1; MB §3 Staff | D9: SR-IN-08 | E9: =INDEX(Requirements!$C$2:$C$28,MATCH(A9,Requirements!$A$2:$A$28,0)) -> High | F9: AC-FR-008-1; AC-FR-008-2 | G9: ADR-M2-01; ADR-M2-03; ADR-M2-04; ADR-M2-05; ADR-M2-06; docs/decisions/README.md | H9: src/CivicConnect.Web/: RequestQueryService; RequestAccessPolicy; EfRequestReader. M2 PR12; M3 PR14; published combined implementation 668795a (PR17). | I9: S04/S05/H08/H09; database checks; passed 2026-10-13 where mapped; docs/testing-m3.md. | J9: M2 requirement/AC unchanged; CR-M3-C01 retained. Bianca/Michael review and PR17 approvals: 14 Oct. Published 668795a; CI verified; docs 15 Oct 2026. | K9: 15 Oct 2026; 668795a; PR17/CI pass. CONDITIONALLY READY: agreed M3 read/status increment, simulated staging only. PED Section 14. | L9: In Development | M9: Access isolation | N9: RequestsController; RequestQueryService | O9: Michael EF Core/PostgreSQL reader and persisted synthetic requests/notes; authorised application projection. | P9: ADR-M2-04: ASP.NET Core MVC/Razor; EF Core/Npgsql 8.0.11; PostgreSQL adapters/migrations implemented by Michael (PR14). | Q9: R-013; R-017 | R9: =INDEX(Requirements!$B$2:$B$28,MATCH(A9,Requirements!$A$2:$A$28,0)) -> Allow authorised staff to view full request details. | S9: Permitted staff sees internal notes; wrong category denied. | T9: Full details omit owner/priority/due-date/requester; AC1 incomplete. See docs/defects.md and technical-debt.md. | U9: docs/testing-m3.md; docs/evidence/m3/personal-20261013-181846/ (integration.txt, regression.txt, database.txt; mapped IDs in column I). | V9: 2026-10-13 18:18-18:19 SAST; Cameron Purdon 601963; f774bf8.
A10: FR-009 | B10: Assign or accept ownership | C10: Staff; PED §2.1.1; MB §3 Staff | D10: SR-IN-09 | E10: =INDEX(Requirements!$C$2:$C$28,MATCH(A10,Requirements!$A$2:$A$28,0)) -> High | F10: AC-FR-009-1; AC-FR-009-2 | G10: ADR-M2-02; ADR-M2-03; ADR-M2-04; ADR-M2-05; ADR-M2-06; docs/decisions/README.md | H10: Planned. Design source PR #10 (architecture) / #11 (data/technology); no application implementation for this row. | I10: Database concurrency mechanism and simultaneous-claim test pending | J10: M2 consolidation 2026-09-30; requirement/AC unchanged; M3 2026-10-13: evidence evolved; requirement/AC unchanged; CR-M3-C01. | K10: 15 Oct 2026; 668795a; PR17/CI pass. CONDITIONALLY READY: agreed M3 read/status increment, simulated staging only. PED Section 14. | L10: Planned | M10: Integrity | N10: Assignment service (planned) | O10: Conditional atomic owner update plus RequestHistory | P10: ADR-M2-04: ASP.NET Core MVC/Razor; EF Core/Npgsql 8.0.11; PostgreSQL adapters/migrations implemented by Michael (PR14). | Q10: R-015 | R10: =INDEX(Requirements!$B$2:$B$28,MATCH(A10,Requirements!$A$2:$A$28,0)) -> Allow authorised staff to assign a request or accept responsibility for it. | S10: Not executed for complete acceptance. | T10: Eligible owner assignment/concurrent claiming absent; Assigned status is not owner assignment. | U10: No complete M3 execution evidence; see docs/release-evidence.md. | V10: 2026-10-13 evidence review.
A11: FR-010 | B11: Controlled status transitions | C11: Staff; PED §2.1.1; MB §3 Staff | D11: SR-IN-10 | E11: =INDEX(Requirements!$C$2:$C$28,MATCH(A11,Requirements!$A$2:$A$28,0)) -> High | F11: AC-FR-010-1; AC-FR-010-2 | G11: ADR-M2-02; ADR-M2-03; ADR-M2-04; ADR-M2-05; ADR-M2-06; docs/decisions/README.md | H11: src/CivicConnect.Web/: StatusTransitionService; RequestStatusService; EfRequestStatusWriter. M2 PR12; M3 PR14; published combined implementation 668795a (PR17). | I11: C01-C06; BB05; A03/A05/A06; E01/E02; passed 2026-10-13 where mapped; docs/testing-m3.md. | J11: Original requirement/AC unchanged. CR-M3-C03: team M3 scope confirmed 15 Oct; read/status increment conditionally ready in controlled simulation. PR17 and combined CI complete. | K11: 15 Oct 2026; 668795a; PR17/CI pass. CONDITIONALLY READY: agreed M3 read/status increment, simulated staging only. PED Section 14. | L11: In Development | M11: Integrity; testability | N11: StatusTransitionService; six State classes; RequestStatusService | O11: PostgreSQL status/history/public-note transaction and optimistic version; broader schema/acceptance gaps remain. | P11: ADR-M2-04: ASP.NET Core MVC/Razor; EF Core/Npgsql 8.0.11; PostgreSQL adapters/migrations implemented by Michael (PR14). | Q11: R-011; R-027; R-047 closed for tested lifecycle; TD-04 closed for reviewed architecture (14 Oct 2026). | R11: =INDEX(Requirements!$B$2:$B$28,MATCH(A11,Requirements!$A$2:$A$28,0)) -> Allow request status changes only through the agreed lifecycle. | S11: Legal lifecycle saved with actor/time/history; invalid/unauthorised/stale changes rejected. | T11: Synthetic identities; simultaneous HTTP/audit coverage limited. Team accepts controlled M3 simulation; live accounts and full product remain incomplete for M4 finalisation. | U11: docs/testing-m3.md; docs/evidence/m3/personal-20261013-181846/ (integration.txt, regression.txt, database.txt; mapped IDs in column I). | V11: 2026-10-13 18:18-18:19 SAST; Cameron Purdon 601963; f774bf8.
A12: FR-011 | B12: Record actions and notes | C12: Staff; PED §2.1.1; MB §3 Staff | D12: SR-IN-11 | E12: =INDEX(Requirements!$C$2:$C$28,MATCH(A12,Requirements!$A$2:$A$28,0)) -> High | F12: AC-FR-011-1; AC-FR-011-2 | G12: ADR-M2-03; ADR-M2-04; ADR-M2-05; ADR-M2-06; docs/decisions/README.md | H12: src/CivicConnect.Web/: DTO note filtering; EfRequestStatusWriter public feedback. M2 PR12; M3 PR14; published combined implementation 668795a (PR17). | I12: S02/H05; BB03/BB04; E01/E02; passed 2026-10-13 where mapped; docs/testing-m3.md. | J12: M2 requirement/AC unchanged; CR-M3-C01 retained. Bianca/Michael review and PR17 approvals: 14 Oct. Published 668795a; CI verified; docs 15 Oct 2026. | K12: 15 Oct 2026; 668795a; PR17/CI pass. CONDITIONALLY READY: agreed M3 read/status increment, simulated staging only. PED Section 14. | L12: In Development | M12: Access isolation; integrity | N12: RequestQueryService note projection; transactional status-related public-note writer; general note workflow unimplemented | O12: PostgreSQL status/history/public-note transaction and optimistic version; broader schema/acceptance gaps remain. | P12: ADR-M2-04: ASP.NET Core MVC/Razor; EF Core/Npgsql 8.0.11; PostgreSQL adapters/migrations implemented by Michael (PR14). | Q12: R-017 | R12: =INDEX(Requirements!$B$2:$B$28,MATCH(A12,Requirements!$A$2:$A$28,0)) -> Allow staff to record comments, actions and resolution notes against a request. | S12: Internal notes excluded from owner response; invalid feedback produces no writes. | T12: General note author/time/correction workflow absent. See docs/defects.md and technical-debt.md. | U12: docs/testing-m3.md; docs/evidence/m3/personal-20261013-181846/ (integration.txt, regression.txt, database.txt; mapped IDs in column I). | V12: 2026-10-13 18:18-18:19 SAST; Cameron Purdon 601963; f774bf8.
A13: FR-012 | B13: Resolve and close requests | C13: Staff; PED §2.1.1; MB §3 Staff | D13: SR-IN-12 | E13: =INDEX(Requirements!$C$2:$C$28,MATCH(A13,Requirements!$A$2:$A$28,0)) -> High | F13: AC-FR-012-1; AC-FR-012-2 | G13: ADR-M2-02; ADR-M2-03; ADR-M2-04; ADR-M2-05; ADR-M2-06; docs/decisions/README.md | H13: src/CivicConnect.Web/: StatusTransitionService; RequestStatusService; status POST. M2 PR12; M3 PR14; published combined implementation 668795a (PR17). | I13: E01/E02; C01/C02; passed 2026-10-13 where mapped; docs/testing-m3.md. | J13: M2 requirement/AC unchanged; CR-M3-C01 retained. Bianca/Michael review and PR17 approvals: 14 Oct. Published 668795a; CI verified; docs 15 Oct 2026. | K13: 15 Oct 2026; 668795a; PR17/CI pass. CONDITIONALLY READY: agreed M3 read/status increment, simulated staging only. PED Section 14. | L13: In Development | M13: Integrity; access isolation | N13: RequestStatusService; State rules for resolution and closure; transactional history/feedback writer | O13: PostgreSQL status/history/public-note transaction and optimistic version; broader schema/acceptance gaps remain. | P13: ADR-M2-04: ASP.NET Core MVC/Razor; EF Core/Npgsql 8.0.11; PostgreSQL adapters/migrations implemented by Michael (PR14). | Q13: R-011; R-027; R-047 closed for tested lifecycle; TD-04 closed for reviewed architecture (14 Oct 2026). | R13: =INDEX(Requirements!$B$2:$B$28,MATCH(A13,Requirements!$A$2:$A$28,0)) -> Allow authorised staff to resolve and close requests. | S13: Staff resolves with summary then closes; terminal reopen denied. | T13: Broader live account/permission acceptance pending. See docs/defects.md and technical-debt.md. | U13: docs/testing-m3.md; docs/evidence/m3/personal-20261013-181846/ (integration.txt, regression.txt, database.txt; mapped IDs in column I). | V13: 2026-10-13 18:18-18:19 SAST; Cameron Purdon 601963; f774bf8.
... A28: NFR-009 | B28: Testability of core business rules | C28: Project team; PED §5.2 concern 4; MB §15; M1 §4 | D28: Cross-cutting: core request lifecycle | E28: =INDEX(Requirements!$C$2:$C$28,MATCH(A28,Requirements!$A$2:$A$28,0)) -> High | F28: AC-NFR-009-1; AC-NFR-009-2 | G28: ADR-M2-01; ADR-M2-04; ADR-M2-05; ADR-M2-06; ADR-M2-07; docs/decisions/README.md | H28: src/CivicConnect.Web/: Injected reader/policy/writer; isolated executable suites. M2 PR12; M3 PR14; published combined implementation 668795a (PR17). | I28: C01-C06; BB01-BB05; A01-A06; E01/E02; passed 2026-10-13 where mapped; docs/testing-m3.md. | J28: M2 requirement/AC unchanged; CR-M3-C01 retained. Bianca/Michael review and PR17 approvals: 14 Oct. Published 668795a; CI verified; docs 15 Oct 2026. | K28: 15 Oct 2026; 668795a; PR17/CI pass. CONDITIONALLY READY: agreed M3 read/status increment, simulated staging only. PED Section 14. | L28: In Development | M28: Testability | N28: Injected reader/policy; verification executable | O28: Synthetic data with controlled store fault | P28: ADR-M2-04: ASP.NET Core MVC/Razor; EF Core/Npgsql 8.0.11; PostgreSQL adapters/migrations implemented by Michael (PR14). | Q28: R-009; R-038; R-047 closed for tested lifecycle; R-053 closed for current combined CI coverage (run 38594557024). | R28: =INDEX(Requirements!$B$2:$B$28,MATCH(A28,Requirements!$A$2:$A$28,0)) -> Allow core request rules to be tested with controlled data in a separate test environment. | S28: Repeatable core access/status cases; negative control fails forbidden transition. | T28: Submission/assignment/reporting and real login remain original requirements planned for M4 finalisation; current evidence covers the agreed M3 read/status increment. | U28: Personal run: docs/evidence/m3/personal-20261013-181846/; IDs in I28. Combined main CI: https://github.com/Michael-Ellis819/Virtual_Group_K_SEN381_Project/actions/runs/38594557024 on 668795a; regression/database/M3/performance, analysis and dependency checks pass. | V28: 2026-10-13 18:18-18:19 SAST; Cameron Purdon 601963; f774bf8.
A31: Source key | B31: PED = supplied PED1, sections 1.2 and 2.1–2.2. MB = SEN381 CivicConnect Master Project Brief, sections 3 and 11.
A32: RTM format | B32: Original requirements/ACs retained. Published 668795a; PR17 approvals and main CI 38594557024 pass. Cameron confirmed team M3 read/status scope on 15 Oct 2026. CONDITIONALLY READY for controlled simulated staging; CR-M3-C03 and PED Section 14.
A33: Status | B33: Planned = no working implementation. In Development = partial evidence; full acceptance unverified. Team plans unfinished original features for M4 finalisation; no requirements removed. M3 conditional readiness applies only to the agreed increment and simulation.
A34: Maintenance | B34: Keep requirement IDs stable. Update affected acceptance criteria and trace links when a change is approved. Add actual evidence links as work progresses.
A35: Source PR 10 | B35: https://github.com/Michael-Ellis819/Virtual_Group_K_SEN381_Project/pull/10
A36: Source PR 11 | B36: https://github.com/Michael-Ellis819/Virtual_Group_K_SEN381_Project/pull/11
A37: M1 history | B37: https://github.com/Michael-Ellis819/Virtual_Group_K_SEN381_Project/pull/3
A38: Local evidence | B38: docs/evidence/local-verification.txt; checked 2026-09-30; 29 service/HTTP checks passed; fixture only

Sheet Requirements
A1: ID | B1: Requirement | C1: Priority | D1: Acceptance criterion 1 | E1: Acceptance criterion 2
A2: FR-001 | B2: Allow requesters to submit a request with a category, description and location. | C2: High | D2: AC-FR-001-1: A valid submission saves one request with a unique reference, date and New status. | E2: AC-FR-001-2: Missing required fields or an invalid category are rejected without saving a request.
A3: FR-002 | B3: Use a predefined list of request categories. | C3: High | D3: AC-FR-002-1: A requester can select and save a category from the agreed list. | E3: AC-FR-002-2: An unlisted category is rejected; existing requests retain their saved category.
A4: FR-003 | B4: Allow requesters to view the current status of their own requests. | C4: High | D4: AC-FR-003-1: After an authorised update, the requester sees the saved status and update date. | E4: AC-FR-003-2: Entering another requester’s reference does not reveal its status or details.
A5: FR-004 | B5: Allow requesters to view their previous requests. | C5: Medium | D5: AC-FR-004-1: The list shows each own request’s reference, category, date and current status, including completed requests. | E5: AC-FR-004-2: Other users’ requests are excluded; an empty list displays a clear message.
A6: FR-005 | B6: Provide requester feedback when a request is accepted, rejected, updated or completed. | C6: Medium | D6: AC-FR-005-1: Each event produces feedback showing the event, date and current status; rejection and completion include a reason or summary. | E6: AC-FR-005-2: Feedback remains available later and excludes private staff notes and other users’ information.
A7: FR-006 | B7: Allow staff to view requests permitted by their role and assigned categories. | C7: High | D7: AC-FR-006-1: Staff see all and only the requests allowed by their permissions. | E7: AC-FR-006-2: Direct access to a request outside these permissions is denied.
A8: FR-007 | B8: Allow staff to search requests and filter by status, category, date and priority, and sort by date or priority. | C8: Medium | D8: AC-FR-007-1: Searches and combined filters return only matching authorised records, including both date-range boundaries. | E8: AC-FR-007-2: Sorting gives the expected order; clearing filters restores the list and no matches displays an empty result.
A9: FR-008 | B9: Allow authorised staff to view full request details. | C9: High | D9: AC-FR-008-1: Details show the reference, requester, category, description, location, date, status, priority, owner, due date and notes. | E9: AC-FR-008-2: Unauthorised users cannot open the same details; missing owner or due date is clearly shown.
A10: FR-009 | B10: Allow authorised staff to assign a request or accept responsibility for it. | C10: High | D10: AC-FR-009-1: Assignment records one eligible owner, the person making the change and the time. | E10: AC-FR-009-2: Ineligible owners are rejected; simultaneous attempts to claim a request cannot create two owners.
A11: FR-010 | B11: Allow request status changes only through the agreed lifecycle. | C11: High | D11: AC-FR-010-1: Allowed changes save the new status, previous status, actor and time. | E11: AC-FR-010-2: Invalid transitions and changes by unauthorised users are rejected without changing the request.
A12: FR-011 | B12: Allow staff to record comments, actions and resolution notes against a request. | C12: High | D12: AC-FR-011-1: A nonblank entry is saved with its author and time; blank entries are rejected. | E12: AC-FR-011-2: Requester-visible updates reach the requester; internal notes remain private and corrections preserve earlier entries.
... A28: NFR-009 | B28: Allow core request rules to be tested with controlled data in a separate test environment. | C28: High | D28: AC-NFR-009-1: Submission, access, assignment, status and reporting rules accept test inputs and produce observable results without production data. | E28: AC-NFR-009-2: Repeating a check from the same starting state gives the same outcome; deliberately invalid behaviour is detected.
A31: Lifecycle | B31: Requests follow New → Assigned → In Progress → Resolved → Closed. A New request may be rejected with a recorded reason. Open means New, Assigned or In Progress. Reopening is not included.
A32: Permissions and feedback | B32: Requesters view their own requests and public updates. Staff access follows role/category permissions. Management accesses service reporting. Feedback is provided within the application; internal staff notes remain private. Email notifications are not included in the initial version.
A33: Priority and overdue rules | B33: Priorities are Low, Normal and High, with Normal as default. Authorised staff can change priorities and set due dates. An open request is overdue when its due time has passed. Requests without a due date are clearly identified and are not counted as overdue. Automatic escalation remains deferred.
A34: Categories | B34: The initial categories are Facility Faults, Damaged Equipment, Security Concerns, IT Support, Maintenance, Lost Property and Other. Each request must use one category from this list.
A35: Quality targets | B35: The numerical performance, usability and recovery targets in NFR-002, NFR-004 and NFR-007 are acceptance targets for the pilot. Hosting options will be assessed against them in M2. Target changes follow change control. Achievement will be demonstrated through testing in later milestones.
A36: Attachments | B36: File and photo uploads are deferred to future scope to limit storage, security and implementation work. Initial submissions contain a category, description and location.
A37: Scope boundaries | B37: External messaging integrations, payments, multi-tenant support and native apps are excluded from the initial version. Attachments, automated escalation, public APIs, AI categorisation and multilingual support remain future scope. Technology and architecture decisions will be addressed in M2.
